algorithm_logger/__init__.py
algorithm_logger/base.py
algorithm_logger/tests/__init__.py
algorithm_logger/tests/test_base.py
algorithm_logger-0.0.1.dist-info/DESCRIPTION.rst
algorithm_logger-0.0.1.dist-info/METADATA
algorithm_logger-0.0.1.dist-info/RECORD
algorithm_logger-0.0.1.dist-info/WHEEL
algorithm_logger-0.0.1.dist-info/metadata.json
algorithm_logger-0.0.1.dist-info/top_level.txt
