Metadata-Version: 2.0
Name: algorithm-logger
Version: 0.0.1
Summary: Python library for logging and debugging algorithms
Home-page: https://github.com/mbodenhamer/algorithm-logger
Author: Matt Bodenhamer
Author-email: mbodenhamer@mbodenhamer.com
License: MIT
Keywords: algorithm,logging,logger,algorithm logger
Platform: UNKNOWN
Classifier: Development Status :: 2 - Pre-Alpha
Classifier: Environment :: Console
Classifier: Intended Audience :: Developers
Classifier: License :: OSI Approved :: MIT License
Classifier: Operating System :: POSIX :: Linux
Classifier: Programming Language :: Python
Classifier: Programming Language :: Python :: 2.7
Classifier: Programming Language :: Python :: 3.6
Classifier: Topic :: Utilities
Requires-Dist: syn
